[
  {
    "firstName": "Caroline",
    "lastName": "Møller",
    "email": "caroline.moller@example.com",
    "username": "purpleduck447",
    "password": "pakistan",
    "invokedAt": "2022-02-23T00:37:10.056Z"
  },
  {
    "firstName": "Gavin",
    "lastName": "Jenkins",
    "email": "gavin.jenkins@example.com",
    "username": "whiteswan989",
    "password": "friendly",
    "invokedAt": "2022-02-23T01:52:46.893Z"
  },
  {
    "firstName": "Martin",
    "lastName": "Crawford",
    "email": "martin.crawford@example.com",
    "username": "goldentiger517",
    "password": "dude",
    "invokedAt": "2022-02-23T02:25:54.882Z"
  },
  {
    "firstName": "Felecia",
    "lastName": "Campbell",
    "email": "felecia.campbell@example.com",
    "username": "biglion994",
    "password": "motion",
    "invokedAt": "2022-02-23T02:46:42.231Z"
  },
  {
    "firstName": "Dean",
    "lastName": "Willis",
    "email": "dean.willis@example.com",
    "username": "ticklishladybug576",
    "password": "soccer1",
    "invokedAt": "2022-02-23T02:55:41.781Z"
  },
  {
    "firstName": "Egídio",
    "lastName": "Monteiro",
    "email": "egidio.monteiro@example.com",
    "username": "orangesnake123",
    "password": "leedsutd",
    "invokedAt": "2022-02-23T03:06:40.123Z"
  },
  {
    "firstName": "Sofia",
    "lastName": "Olsen",
    "email": "sofia.olsen@example.com",
    "username": "angryduck418",
    "password": "alleycat",
    "invokedAt": "2022-02-23T03:25:21.986Z"
  },
  {
    "firstName": "Matthew",
    "lastName": "Taylor",
    "email": "matthew.taylor@example.com",
    "username": "sadfish121",
    "password": "truck",
    "invokedAt": "2022-02-23T03:35:16.092Z"
  },
  {
    "firstName": "Irísia",
    "lastName": "Nunes",
    "email": "irisia.nunes@example.com",
    "username": "sadwolf925",
    "password": "jello",
    "invokedAt": "2022-02-23T03:43:01.045Z"
  },
  {
    "firstName": "Sátiro",
    "lastName": "Moreira",
    "email": "satiro.moreira@example.com",
    "username": "heavybird384",
    "password": "kisses",
    "invokedAt": "2022-02-23T03:48:48.137Z"
  },
  {
    "firstName": "Daria",
    "lastName": "Abraham",
    "email": "daria.abraham@example.com",
    "username": "goldenostrich839",
    "password": "kick",
    "invokedAt": "2022-02-23T03:54:43.174Z"
  },
  {
    "firstName": "Ayla",
    "lastName": "Rosenberg",
    "email": "ayla.rosenberg@example.com",
    "username": "yellowkoala499",
    "password": "242424",
    "invokedAt": "2022-02-23T04:00:31.070Z"
  },
  {
    "firstName": "Mona",
    "lastName": "Gehrke",
    "email": "mona.gehrke@example.com",
    "username": "whitesnake414",
    "password": "shalom",
    "invokedAt": "2022-02-23T04:21:41.686Z"
  },
  {
    "firstName": "آرش",
    "lastName": "جعفری",
    "email": "arsh.jaafry@example.com",
    "username": "goldenostrich569",
    "password": "andreas",
    "invokedAt": "2022-02-23T04:41:22.974Z"
  },
  {
    "firstName": "Sarah",
    "lastName": "Barnes",
    "email": "sarah.barnes@example.com",
    "username": "happyfish977",
    "password": "rabbits",
    "invokedAt": "2022-02-23T04:52:04.236Z"
  },
  {
    "firstName": "Natalia",
    "lastName": "Mendez",
    "email": "natalia.mendez@example.com",
    "username": "crazyleopard341",
    "password": "francine",
    "invokedAt": "2022-02-23T04:57:51.799Z"
  },
  {
    "firstName": "Henrik",
    "lastName": "Øen",
    "email": "henrik.oen@example.com",
    "username": "purplemouse464",
    "password": "blonds",
    "invokedAt": "2022-02-23T05:10:47.907Z"
  },
  {
    "firstName": "Marianna",
    "lastName": "Gläser",
    "email": "marianna.glaser@example.com",
    "username": "silvergorilla617",
    "password": "typhoon",
    "invokedAt": "2022-02-23T05:23:56.972Z"
  },
  {
    "firstName": "Hanan",
    "lastName": "Arnevik",
    "email": "hanan.arnevik@example.com",
    "username": "organicgorilla843",
    "password": "tabasco",
    "invokedAt": "2022-02-23T05:29:53.088Z"
  },
  {
    "firstName": "Gerhard",
    "lastName": "Sanchez",
    "email": "gerhard.sanchez@example.com",
    "username": "crazytiger454",
    "password": "playstat",
    "invokedAt": "2022-02-23T05:35:46.774Z"
  },
  {
    "firstName": "Lloyd",
    "lastName": "Watkins",
    "email": "lloyd.watkins@example.com",
    "username": "blackwolf977",
    "password": "kicker",
    "invokedAt": "2022-02-23T05:41:29.805Z"
  },
  {
    "firstName": "Natalia",
    "lastName": "Alvarez",
    "email": "natalia.alvarez@example.com",
    "username": "heavybutterfly440",
    "password": "london",
    "invokedAt": "2022-02-23T05:47:23.930Z"
  },
  {
    "firstName": "Gregory",
    "lastName": "Arnold",
    "email": "gregory.arnold@example.com",
    "username": "silvercat503",
    "password": "reserve",
    "invokedAt": "2022-02-23T05:53:25.661Z"
  },
  {
    "firstName": "Torje",
    "lastName": "Throndsen",
    "email": "torje.throndsen@example.com",
    "username": "ticklishgoose396",
    "password": "marshall",
    "invokedAt": "2022-02-23T05:59:09.079Z"
  },
  {
    "firstName": "Timothee",
    "lastName": "Schmitt",
    "email": "timothee.schmitt@example.com",
    "username": "beautifulostrich800",
    "password": "liang",
    "invokedAt": "2022-02-23T06:17:16.790Z"
  },
  {
    "firstName": "سارینا",
    "lastName": "حیدری",
    "email": "sryn.hydry@example.com",
    "username": "angryzebra872",
    "password": "uuuuu",
    "invokedAt": "2022-02-23T06:36:33.237Z"
  },
  {
    "firstName": "Willard",
    "lastName": "Thomas",
    "email": "willard.thomas@example.com",
    "username": "happygoose301",
    "password": "having",
    "invokedAt": "2022-02-23T06:48:48.053Z"
  },
  {
    "firstName": "Benjamin",
    "lastName": "Leclerc",
    "email": "benjamin.leclerc@example.com",
    "username": "orangefish358",
    "password": "sissy",
    "invokedAt": "2022-02-23T06:54:48.637Z"
  },
  {
    "firstName": "Raul",
    "lastName": "Aguilar",
    "email": "raul.aguilar@example.com",
    "username": "tinytiger214",
    "password": "mang",
    "invokedAt": "2022-02-23T07:00:31.803Z"
  },
  {
    "firstName": "Mimon",
    "lastName": "Rodrigues",
    "email": "mimon.rodrigues@example.com",
    "username": "redsnake539",
    "password": "iawgk2",
    "invokedAt": "2022-02-23T07:15:45.122Z"
  },
  {
    "firstName": "Robin",
    "lastName": "Jessen",
    "email": "robin.jessen@example.com",
    "username": "ticklishmeercat386",
    "password": "peggy",
    "invokedAt": "2022-02-23T07:27:00.823Z"
  },
  {
    "firstName": "Leona",
    "lastName": "Leclercq",
    "email": "leona.leclercq@example.com",
    "username": "blackleopard898",
    "password": "336699",
    "invokedAt": "2022-02-23T07:33:01.959Z"
  },
  {
    "firstName": "Bruce",
    "lastName": "Stevens",
    "email": "bruce.stevens@example.com",
    "username": "ticklishladybug997",
    "password": "colin",
    "invokedAt": "2022-02-23T07:39:02.232Z"
  },
  {
    "firstName": "Ayşe",
    "lastName": "Okumuş",
    "email": "ayse.okumus@example.com",
    "username": "beautifulkoala379",
    "password": "bubba123",
    "invokedAt": "2022-02-23T07:44:51.858Z"
  },
  {
    "firstName": "Donald",
    "lastName": "Hayes",
    "email": "donald.hayes@example.com",
    "username": "greenswan740",
    "password": "massimo",
    "invokedAt": "2022-02-23T07:50:44.838Z"
  },
  {
    "firstName": "Emma",
    "lastName": "Hannula",
    "email": "emma.hannula@example.com",
    "username": "reddog686",
    "password": "alberto",
    "invokedAt": "2022-02-23T07:56:33.965Z"
  },
  {
    "firstName": "Klaus-Dieter",
    "lastName": "Liebert",
    "email": "klaus-dieter.liebert@example.com",
    "username": "yellowtiger141",
    "password": "mango",
    "invokedAt": "2022-02-23T08:10:36.885Z"
  },
  {
    "firstName": "Aartje",
    "lastName": "Vaes",
    "email": "aartje.vaes@example.com",
    "username": "brownleopard656",
    "password": "knights",
    "invokedAt": "2022-02-23T08:29:33.067Z"
  },
  {
    "firstName": "Garance",
    "lastName": "Nguyen",
    "email": "garance.nguyen@example.com",
    "username": "brownzebra690",
    "password": "johanna",
    "invokedAt": "2022-02-23T08:39:54.666Z"
  },
  {
    "firstName": "Ivy",
    "lastName": "Jackson",
    "email": "ivy.jackson@example.com",
    "username": "happymouse465",
    "password": "swinger",
    "invokedAt": "2022-02-23T08:45:58.042Z"
  },
  {
    "firstName": "Baptiste",
    "lastName": "Meunier",
    "email": "baptiste.meunier@example.com",
    "username": "silvercat318",
    "password": "asses",
    "invokedAt": "2022-02-23T08:51:54.230Z"
  },
  {
    "firstName": "Batur",
    "lastName": "Eronat",
    "email": "batur.eronat@example.com",
    "username": "reddog907",
    "password": "mustard",
    "invokedAt": "2022-02-23T08:57:55.038Z"
  },
  {
    "firstName": "Todd",
    "lastName": "Pena",
    "email": "todd.pena@example.com",
    "username": "silverrabbit894",
    "password": "vvvvvvvv",
    "invokedAt": "2022-02-23T09:10:34.264Z"
  },
  {
    "firstName": "Danielle",
    "lastName": "Turner",
    "email": "danielle.turner@example.com",
    "username": "purplelion107",
    "password": "2468",
    "invokedAt": "2022-02-23T09:22:35.261Z"
  },
  {
    "firstName": "Corinna",
    "lastName": "Lambert",
    "email": "corinna.lambert@example.com",
    "username": "silverostrich851",
    "password": "down",
    "invokedAt": "2022-02-23T09:28:24.060Z"
  },
  {
    "firstName": "Erin",
    "lastName": "Patterson",
    "email": "erin.patterson@example.com",
    "username": "heavyduck600",
    "password": "ursula",
    "invokedAt": "2022-02-23T09:34:58.048Z"
  },
  {
    "firstName": "Dan",
    "lastName": "Sims",
    "email": "dan.sims@example.com",
    "username": "whitebear401",
    "password": "lambert",
    "invokedAt": "2022-02-23T09:40:59.666Z"
  },
  {
    "firstName": "ماهان",
    "lastName": "کوتی",
    "email": "mhn.khwty@example.com",
    "username": "heavyelephant774",
    "password": "trinidad",
    "invokedAt": "2022-02-23T09:46:55.739Z"
  },
  {
    "firstName": "Elif",
    "lastName": "Akbulut",
    "email": "elif.akbulut@example.com",
    "username": "bluecat713",
    "password": "passwor",
    "invokedAt": "2022-02-23T09:52:53.069Z"
  },
  {
    "firstName": "Darryl",
    "lastName": "Watson",
    "email": "darryl.watson@example.com",
    "username": "tinymouse967",
    "password": "jennifer",
    "invokedAt": "2022-02-23T09:58:37.102Z"
  },
  {
    "firstName": "Ali",
    "lastName": "Erberk",
    "email": "ali.erberk@example.com",
    "username": "greentiger224",
    "password": "mmmmmmm",
    "invokedAt": "2022-02-23T10:14:16.960Z"
  },
  {
    "firstName": "Kayla",
    "lastName": "Wright",
    "email": "kayla.wright@example.com",
    "username": "orangefrog302",
    "password": "michele",
    "invokedAt": "2022-02-23T10:31:16.823Z"
  },
  {
    "firstName": "Irina",
    "lastName": "Chevalier",
    "email": "irina.chevalier@example.com",
    "username": "angrydog437",
    "password": "killme",
    "invokedAt": "2022-02-23T10:40:54.885Z"
  },
  {
    "firstName": "Kati",
    "lastName": "Wörner",
    "email": "kati.worner@example.com",
    "username": "redlion456",
    "password": "swallow",
    "invokedAt": "2022-02-23T10:46:50.733Z"
  },
  {
    "firstName": "Dennis",
    "lastName": "Lopez",
    "email": "dennis.lopez@example.com",
    "username": "yellowgoose524",
    "password": "heineken",
    "invokedAt": "2022-02-23T10:52:44.985Z"
  },
  {
    "firstName": "Katherine",
    "lastName": "Crawford",
    "email": "katherine.crawford@example.com",
    "username": "silverkoala323",
    "password": "wolfpack",
    "invokedAt": "2022-02-23T10:58:55.323Z"
  },
  {
    "firstName": "Kim",
    "lastName": "Roggeveen",
    "email": "kim.roggeveen@example.com",
    "username": "bigcat868",
    "password": "this",
    "invokedAt": "2022-02-23T11:11:16.357Z"
  },
  {
    "firstName": "Aleksi",
    "lastName": "Wirtanen",
    "email": "aleksi.wirtanen@example.com",
    "username": "happyfish437",
    "password": "dave",
    "invokedAt": "2022-02-23T11:23:09.787Z"
  },
  {
    "firstName": "James",
    "lastName": "Singh",
    "email": "james.singh@example.com",
    "username": "heavyladybug657",
    "password": "palmtree",
    "invokedAt": "2022-02-23T11:29:04.378Z"
  },
  {
    "firstName": "Stephanie",
    "lastName": "Terry",
    "email": "stephanie.terry@example.com",
    "username": "organicmeercat500",
    "password": "camel",
    "invokedAt": "2022-02-23T11:35:14.869Z"
  },
  {
    "firstName": "ماهان",
    "lastName": "سلطانی نژاد",
    "email": "mhn.sltnynjd@example.com",
    "username": "greenfrog132",
    "password": "basket",
    "invokedAt": "2022-02-23T11:41:12.131Z"
  },
  {
    "firstName": "Marit",
    "lastName": "Woldseth",
    "email": "marit.woldseth@example.com",
    "username": "ticklishtiger100",
    "password": "insomnia",
    "invokedAt": "2022-02-23T11:47:00.284Z"
  },
  {
    "firstName": "Jónatas",
    "lastName": "Rocha",
    "email": "jonatas.rocha@example.com",
    "username": "beautifulzebra186",
    "password": "guitar",
    "invokedAt": "2022-02-23T11:52:52.953Z"
  },
  {
    "firstName": "David",
    "lastName": "Klemm",
    "email": "david.klemm@example.com",
    "username": "happysnake364",
    "password": "robins",
    "invokedAt": "2022-02-23T11:58:39.881Z"
  },
  {
    "firstName": "Nicoline",
    "lastName": "Madsen",
    "email": "nicoline.madsen@example.com",
    "username": "lazyduck543",
    "password": "hansolo",
    "invokedAt": "2022-02-23T12:22:12.812Z"
  },
  {
    "firstName": "Lucy",
    "lastName": "Perrin",
    "email": "lucy.perrin@example.com",
    "username": "blackostrich464",
    "password": "trevor",
    "invokedAt": "2022-02-23T12:50:13.417Z"
  },
  {
    "firstName": "Gabriel",
    "lastName": "Morris",
    "email": "gabriel.morris@example.com",
    "username": "lazylion166",
    "password": "boiler",
    "invokedAt": "2022-02-23T13:08:00.066Z"
  },
  {
    "firstName": "Elizabeth",
    "lastName": "Perez",
    "email": "elizabeth.perez@example.com",
    "username": "smallzebra165",
    "password": "erection",
    "invokedAt": "2022-02-23T13:27:47.679Z"
  },
  {
    "firstName": "Andreas",
    "lastName": "Deckers",
    "email": "andreas.deckers@example.com",
    "username": "yellowswan732",
    "password": "champion",
    "invokedAt": "2022-02-23T13:36:20.231Z"
  },
  {
    "firstName": "Victor",
    "lastName": "Christensen",
    "email": "victor.christensen@example.com",
    "username": "beautifulkoala936",
    "password": "soprano",
    "invokedAt": "2022-02-23T13:42:12.303Z"
  },
  {
    "firstName": "Omayma",
    "lastName": "Van de Wijngaard",
    "email": "omayma.vandewijngaard@example.com",
    "username": "angrygoose598",
    "password": "casper",
    "invokedAt": "2022-02-23T13:48:08.059Z"
  },
  {
    "firstName": "Jesse",
    "lastName": "Harju",
    "email": "jesse.harju@example.com",
    "username": "yellowzebra289",
    "password": "252525",
    "invokedAt": "2022-02-23T13:54:00.132Z"
  },
  {
    "firstName": "Zara",
    "lastName": "Chen",
    "email": "zara.chen@example.com",
    "username": "smallostrich330",
    "password": "coolman",
    "invokedAt": "2022-02-23T13:59:48.954Z"
  },
  {
    "firstName": "Alexandra",
    "lastName": "Hammeren",
    "email": "alexandra.hammeren@example.com",
    "username": "silvermeercat347",
    "password": "custom",
    "invokedAt": "2022-02-23T14:14:23.881Z"
  },
  {
    "firstName": "Jessika",
    "lastName": "Schaal",
    "email": "jessika.schaal@example.com",
    "username": "orangeleopard618",
    "password": "barton",
    "invokedAt": "2022-02-23T14:26:21.071Z"
  },
  {
    "firstName": "Aino",
    "lastName": "Kallio",
    "email": "aino.kallio@example.com",
    "username": "sadzebra740",
    "password": "chilli",
    "invokedAt": "2022-02-23T14:32:55.469Z"
  },
  {
    "firstName": "Karl-Dieter",
    "lastName": "Höppner",
    "email": "karl-dieter.hoppner@example.com",
    "username": "orangegorilla443",
    "password": "123789",
    "invokedAt": "2022-02-23T14:39:19.991Z"
  },
  {
    "firstName": "Daryl",
    "lastName": "Barrett",
    "email": "daryl.barrett@example.com",
    "username": "bluepeacock724",
    "password": "wetter",
    "invokedAt": "2022-02-23T14:45:17.675Z"
  },
  {
    "firstName": "Latife",
    "lastName": "Toraman",
    "email": "latife.toraman@example.com",
    "username": "greenmeercat173",
    "password": "ou8122",
    "invokedAt": "2022-02-23T14:51:10.770Z"
  },
  {
    "firstName": "Karla",
    "lastName": "Sørensen",
    "email": "karla.sorensen@example.com",
    "username": "crazybutterfly183",
    "password": "password2",
    "invokedAt": "2022-02-23T14:57:04.307Z"
  },
  {
    "firstName": "Maria",
    "lastName": "Holt",
    "email": "maria.holt@example.com",
    "username": "redswan323",
    "password": "bottom",
    "invokedAt": "2022-02-23T15:10:09.149Z"
  },
  {
    "firstName": "Lance",
    "lastName": "Brown",
    "email": "lance.brown@example.com",
    "username": "yellowbutterfly645",
    "password": "mustang6",
    "invokedAt": "2022-02-23T15:28:46.231Z"
  }
]