[
  {
    "firstName": "Mustafa",
    "lastName": "Ekşioğlu",
    "email": "mustafa.eksioglu@example.com",
    "username": "lazymeercat369",
    "password": "donjuan",
    "invokedAt": "2022-05-03T00:29:01.277Z"
  },
  {
    "firstName": "Jennifer",
    "lastName": "Thomas",
    "email": "jennifer.thomas@example.com",
    "username": "bigbear500",
    "password": "renault",
    "invokedAt": "2022-05-03T02:37:50.330Z"
  },
  {
    "firstName": "Hélder",
    "lastName": "Moura",
    "email": "helder.moura@example.com",
    "username": "blackostrich638",
    "password": "football1",
    "invokedAt": "2022-05-03T03:41:38.466Z"
  },
  {
    "firstName": "Maddison",
    "lastName": "King",
    "email": "maddison.king@example.com",
    "username": "yellowlion582",
    "password": "suzanne",
    "invokedAt": "2022-05-03T04:14:23.595Z"
  },
  {
    "firstName": "پارمیس",
    "lastName": "حسینی",
    "email": "prmys.hsyny@example.com",
    "username": "bigpanda739",
    "password": "aaron",
    "invokedAt": "2022-05-03T04:48:20.127Z"
  },
  {
    "firstName": "Julie",
    "lastName": "Wood",
    "email": "julie.wood@example.com",
    "username": "organicswan157",
    "password": "southpar",
    "invokedAt": "2022-05-03T05:03:36.266Z"
  },
  {
    "firstName": "Juanita",
    "lastName": "Pena",
    "email": "juanita.pena@example.com",
    "username": "yellowsnake515",
    "password": "parrot",
    "invokedAt": "2022-05-03T05:26:03.240Z"
  },
  {
    "firstName": "Paul",
    "lastName": "Boyer",
    "email": "paul.boyer@example.com",
    "username": "bigbear182",
    "password": "rrrrrrr",
    "invokedAt": "2022-05-03T05:37:53.302Z"
  },
  {
    "firstName": "Erik",
    "lastName": "Harris",
    "email": "erik.harris@example.com",
    "username": "crazydog240",
    "password": "easter",
    "invokedAt": "2022-05-03T05:45:06.840Z"
  },
  {
    "firstName": "Logan",
    "lastName": "Edwards",
    "email": "logan.edwards@example.com",
    "username": "orangebutterfly557",
    "password": "1225",
    "invokedAt": "2022-05-03T05:50:58.201Z"
  },
  {
    "firstName": "Imogen",
    "lastName": "Jones",
    "email": "imogen.jones@example.com",
    "username": "bluebird369",
    "password": "bowser",
    "invokedAt": "2022-05-03T05:56:51.997Z"
  },
  {
    "firstName": "ماهان",
    "lastName": "محمدخان",
    "email": "mhn.mhmdkhn@example.com",
    "username": "smallmeercat315",
    "password": "disco",
    "invokedAt": "2022-05-03T06:13:02.500Z"
  },
  {
    "firstName": "Yves",
    "lastName": "Thomas",
    "email": "yves.thomas@example.com",
    "username": "blackbird903",
    "password": "pornporn",
    "invokedAt": "2022-05-03T06:37:19.095Z"
  },
  {
    "firstName": "Jasmine",
    "lastName": "Pelletier",
    "email": "jasmine.pelletier@example.com",
    "username": "greenkoala468",
    "password": "hotbox",
    "invokedAt": "2022-05-03T06:53:01.066Z"
  },
  {
    "firstName": "Ünal",
    "lastName": "Branderhorst",
    "email": "unal.branderhorst@example.com",
    "username": "silvergorilla699",
    "password": "breeze",
    "invokedAt": "2022-05-03T06:58:50.138Z"
  },
  {
    "firstName": "Claus-Peter",
    "lastName": "Willms",
    "email": "claus-peter.willms@example.com",
    "username": "silverzebra220",
    "password": "kenshin",
    "invokedAt": "2022-05-03T07:14:39.615Z"
  },
  {
    "firstName": "Yi",
    "lastName": "Vink",
    "email": "yi.vink@example.com",
    "username": "whiteladybug876",
    "password": "angus1",
    "invokedAt": "2022-05-03T07:29:59.409Z"
  },
  {
    "firstName": "Dirk",
    "lastName": "Pabst",
    "email": "dirk.pabst@example.com",
    "username": "yellowbear833",
    "password": "hawaii",
    "invokedAt": "2022-05-03T07:38:51.392Z"
  },
  {
    "firstName": "Brooke",
    "lastName": "Fitzgerald",
    "email": "brooke.fitzgerald@example.com",
    "username": "organicmouse564",
    "password": "lancia",
    "invokedAt": "2022-05-03T07:44:51.921Z"
  },
  {
    "firstName": "Arthur",
    "lastName": "Watson",
    "email": "arthur.watson@example.com",
    "username": "silvermouse828",
    "password": "smurf",
    "invokedAt": "2022-05-03T07:50:51.134Z"
  }
]