[
  {
    "firstName": "Esteban",
    "lastName": "Diaz",
    "email": "esteban.diaz@example.com",
    "username": "heavygorilla534",
    "password": "smegma",
    "invokedAt": "2024-08-19T00:33:32.491Z"
  },
  {
    "firstName": "Fabien",
    "lastName": "Louis",
    "email": "fabien.louis@example.com",
    "username": "happyostrich222",
    "password": "smoke",
    "invokedAt": "2024-08-19T01:50:17.317Z"
  },
  {
    "firstName": "Cecilie",
    "lastName": "Sørensen",
    "email": "cecilie.sorensen@example.com",
    "username": "heavyduck432",
    "password": "semper",
    "invokedAt": "2024-08-19T02:31:15.211Z"
  },
  {
    "firstName": "Charlotte",
    "lastName": "Mckinney",
    "email": "charlotte.mckinney@example.com",
    "username": "goldenmeercat410",
    "password": "bond007",
    "invokedAt": "2024-08-19T02:50:59.753Z"
  },
  {
    "firstName": "Vemund",
    "lastName": "Haukenes",
    "email": "vemund.haukenes@example.com",
    "username": "tinypanda843",
    "password": "whiteboy",
    "invokedAt": "2024-08-19T02:56:40.209Z"
  },
  {
    "firstName": "Siddharth",
    "lastName": "Nair",
    "email": "siddharth.nair@example.com",
    "username": "sadpanda243",
    "password": "fireblad",
    "invokedAt": "2024-08-19T03:11:25.946Z"
  },
  {
    "firstName": "Inés",
    "lastName": "Román",
    "email": "ines.roman@example.com",
    "username": "organicostrich613",
    "password": "macaroni",
    "invokedAt": "2024-08-19T03:27:38.520Z"
  },
  {
    "firstName": "Anna-Marie",
    "lastName": "Drechsler",
    "email": "anna-marie.drechsler@example.com",
    "username": "crazyelephant843",
    "password": "1007",
    "invokedAt": "2024-08-19T03:36:09.713Z"
  },
  {
    "firstName": "Estelle",
    "lastName": "Moreau",
    "email": "estelle.moreau@example.com",
    "username": "silverbird639",
    "password": "russell",
    "invokedAt": "2024-08-19T03:41:57.533Z"
  },
  {
    "firstName": "Tatiana",
    "lastName": "Vlahović",
    "email": "tatiana.vlahovic@example.com",
    "username": "sadladybug297",
    "password": "nikita",
    "invokedAt": "2024-08-19T03:48:07.557Z"
  },
  {
    "firstName": "Lisa",
    "lastName": "Laurent",
    "email": "lisa.laurent@example.com",
    "username": "beautifulmeercat534",
    "password": "really",
    "invokedAt": "2024-08-19T03:53:53.034Z"
  },
  {
    "firstName": "Loulou",
    "lastName": "Coşkun",
    "email": "loulou.coskun@example.com",
    "username": "greengoose489",
    "password": "rosario",
    "invokedAt": "2024-08-19T03:59:47.308Z"
  },
  {
    "firstName": "Dylan",
    "lastName": "Evans",
    "email": "dylan.evans@example.com",
    "username": "redbutterfly963",
    "password": "909090",
    "invokedAt": "2024-08-19T04:18:23.946Z"
  },
  {
    "firstName": "Lotta",
    "lastName": "Pietila",
    "email": "lotta.pietila@example.com",
    "username": "bluebutterfly464",
    "password": "username",
    "invokedAt": "2024-08-19T04:31:35.091Z"
  },
  {
    "firstName": "Carmelo",
    "lastName": "Gutiérrez",
    "email": "carmelo.gutierrez@example.com",
    "username": "organicbutterfly903",
    "password": "1957",
    "invokedAt": "2024-08-19T04:39:51.077Z"
  },
  {
    "firstName": "Aubrey",
    "lastName": "Andersen",
    "email": "aubrey.andersen@example.com",
    "username": "beautifulrabbit470",
    "password": "1968",
    "invokedAt": "2024-08-19T04:45:52.813Z"
  },
  {
    "firstName": "Tiffany",
    "lastName": "Bennett",
    "email": "tiffany.bennett@example.com",
    "username": "yellowgoose267",
    "password": "freeman",
    "invokedAt": "2024-08-19T04:51:48.105Z"
  }
]