[
  {
    "firstName": "Lena",
    "lastName": "Hasselberg",
    "email": "lena.hasselberg@example.com",
    "username": "happyzebra423",
    "password": "screen",
    "invokedAt": "2025-05-02T00:43:01.308Z"
  },
  {
    "firstName": "Martha",
    "lastName": "Caldwell",
    "email": "martha.caldwell@example.com",
    "username": "silvergorilla343",
    "password": "clean",
    "invokedAt": "2025-05-02T02:20:48.401Z"
  },
  {
    "firstName": "Potishana",
    "lastName": "Kostyuchenko",
    "email": "potishana.kostyuchenko@example.com",
    "username": "sadladybug869",
    "password": "akira",
    "invokedAt": "2025-05-02T03:15:54.203Z"
  },
  {
    "firstName": "Gabrielle",
    "lastName": "Chu",
    "email": "gabrielle.chu@example.com",
    "username": "redbird997",
    "password": "letmein1",
    "invokedAt": "2025-05-02T03:47:31.391Z"
  },
  {
    "firstName": "Cory",
    "lastName": "Evans",
    "email": "cory.evans@example.com",
    "username": "ticklishbird428",
    "password": "wizard1",
    "invokedAt": "2025-05-02T03:58:52.255Z"
  },
  {
    "firstName": "Claudeci",
    "lastName": "Nogueira",
    "email": "claudeci.nogueira@example.com",
    "username": "greensnake451",
    "password": "pickup",
    "invokedAt": "2025-05-02T04:19:35.916Z"
  }
]