[
  {
    "firstName": "Frederikke",
    "lastName": "Poulsen",
    "email": "frederikke.poulsen@example.com",
    "username": "happyzebra822",
    "password": "tottenham",
    "invokedAt": "2026-03-27T01:01:44.918Z"
  },
  {
    "firstName": "Norman",
    "lastName": "Olson",
    "email": "norman.olson@example.com",
    "username": "yellowgoose840",
    "password": "lorraine",
    "invokedAt": "2026-03-27T03:50:54.057Z"
  },
  {
    "firstName": "Vickie",
    "lastName": "Patterson",
    "email": "vickie.patterson@example.com",
    "username": "tinypanda908",
    "password": "abcdefg",
    "invokedAt": "2026-03-27T05:26:22.338Z"
  },
  {
    "firstName": "Túlio",
    "lastName": "Araújo",
    "email": "tulio.araujo@example.com",
    "username": "beautifulmouse157",
    "password": "waffle",
    "invokedAt": "2026-03-27T06:42:24.255Z"
  },
  {
    "firstName": "Branka",
    "lastName": "Dinčić",
    "email": "branka.dincic@example.com",
    "username": "organicfrog137",
    "password": "hollywoo",
    "invokedAt": "2026-03-27T07:44:06.968Z"
  },
  {
    "firstName": "Oscar",
    "lastName": "Patel",
    "email": "oscar.patel@example.com",
    "username": "blackfish217",
    "password": "poiuy",
    "invokedAt": "2026-03-27T08:29:09.618Z"
  },
  {
    "firstName": "Gonca",
    "lastName": "Abacı",
    "email": "gonca.abaci@example.com",
    "username": "greentiger302",
    "password": "studman",
    "invokedAt": "2026-03-27T09:12:58.867Z"
  },
  {
    "firstName": "Alexandre",
    "lastName": "Gagnon",
    "email": "alexandre.gagnon@example.com",
    "username": "greensnake597",
    "password": "ramsey",
    "invokedAt": "2026-03-27T10:05:32.451Z"
  },
  {
    "firstName": "Frida",
    "lastName": "Echeverría",
    "email": "frida.echeverria@example.com",
    "username": "biggorilla566",
    "password": "domingo",
    "invokedAt": "2026-03-27T10:59:15.417Z"
  },
  {
    "firstName": "Osmomisla",
    "lastName": "Petrichenko",
    "email": "osmomisla.petrichenko@example.com",
    "username": "orangeostrich674",
    "password": "young",
    "invokedAt": "2026-03-27T11:40:22.855Z"
  },
  {
    "firstName": "Stefanie",
    "lastName": "Deschamps",
    "email": "stefanie.deschamps@example.com",
    "username": "heavyleopard757",
    "password": "winston",
    "invokedAt": "2026-03-27T12:07:22.902Z"
  },
  {
    "firstName": "Lenni",
    "lastName": "Ylitalo",
    "email": "lenni.ylitalo@example.com",
    "username": "bigswan508",
    "password": "stallion",
    "invokedAt": "2026-03-27T13:39:05.215Z"
  },
  {
    "firstName": "José Luis",
    "lastName": "Rodríguez",
    "email": "joseluis.rodriguez@example.com",
    "username": "redfish470",
    "password": "speaker",
    "invokedAt": "2026-03-27T14:33:17.378Z"
  },
  {
    "firstName": "Tom",
    "lastName": "Gilbert",
    "email": "tom.gilbert@example.com",
    "username": "tinyleopard193",
    "password": "mail",
    "invokedAt": "2026-03-27T15:26:02.216Z"
  },
  {
    "firstName": "Nurdan",
    "lastName": "Yeşilkaya",
    "email": "nurdan.yesilkaya@example.com",
    "username": "goldentiger147",
    "password": "december",
    "invokedAt": "2026-03-27T16:10:07.296Z"
  },
  {
    "firstName": "امیر",
    "lastName": "سالاری",
    "email": "myr.slry@example.com",
    "username": "greenbutterfly609",
    "password": "neng",
    "invokedAt": "2026-03-27T17:07:38.271Z"
  },
  {
    "firstName": "Mercedes",
    "lastName": "Ramos",
    "email": "mercedes.ramos@example.com",
    "username": "brownpeacock297",
    "password": "killme",
    "invokedAt": "2026-03-27T17:58:17.012Z"
  },
  {
    "firstName": "Priscilla",
    "lastName": "Ray",
    "email": "priscilla.ray@example.com",
    "username": "blackladybug853",
    "password": "sword",
    "invokedAt": "2026-03-27T18:51:11.724Z"
  },
  {
    "firstName": "Manbir",
    "lastName": "Belligatti",
    "email": "manbir.belligatti@example.com",
    "username": "tinylion439",
    "password": "mybaby",
    "invokedAt": "2026-03-27T19:32:07.179Z"
  },
  {
    "firstName": "Phoenix",
    "lastName": "Thompson",
    "email": "phoenix.thompson@example.com",
    "username": "blackfrog705",
    "password": "oasis",
    "invokedAt": "2026-03-27T19:59:54.223Z"
  },
  {
    "firstName": "Paige",
    "lastName": "Hughes",
    "email": "paige.hughes@example.com",
    "username": "heavyladybug999",
    "password": "ultra",
    "invokedAt": "2026-03-27T20:39:49.936Z"
  },
  {
    "firstName": "Barb",
    "lastName": "Parker",
    "email": "barb.parker@example.com",
    "username": "goldenzebra846",
    "password": "sims",
    "invokedAt": "2026-03-27T21:06:37.313Z"
  },
  {
    "firstName": "Kent",
    "lastName": "Williams",
    "email": "kent.williams@example.com",
    "username": "redkoala536",
    "password": "billy",
    "invokedAt": "2026-03-27T21:48:12.975Z"
  },
  {
    "firstName": "Volkan",
    "lastName": "Ekşioğlu",
    "email": "volkan.eksioglu@example.com",
    "username": "beautifulpeacock922",
    "password": "brasil",
    "invokedAt": "2026-03-27T22:03:15.211Z"
  }
]