[
  {
    "firstName": "Solomon",
    "lastName": "Zaplavskiy",
    "email": "solomon.zaplavskiy@example.com",
    "username": "beautifulostrich547",
    "password": "castle",
    "invokedAt": "2026-07-19T01:11:31.178Z"
  },
  {
    "firstName": "Isabella",
    "lastName": "Lavoie",
    "email": "isabella.lavoie@example.com",
    "username": "blackrabbit366",
    "password": "1114",
    "invokedAt": "2026-07-19T04:31:46.466Z"
  },
  {
    "firstName": "Valerie",
    "lastName": "Sutton",
    "email": "valerie.sutton@example.com",
    "username": "silvertiger153",
    "password": "hun999",
    "invokedAt": "2026-07-19T07:06:00.453Z"
  },
  {
    "firstName": "Jeremy",
    "lastName": "Chu",
    "email": "jeremy.chu@example.com",
    "username": "silvermeercat218",
    "password": "happy2",
    "invokedAt": "2026-07-19T09:11:03.158Z"
  },
  {
    "firstName": "Jason",
    "lastName": "Burke",
    "email": "jason.burke@example.com",
    "username": "ticklishostrich986",
    "password": "fullback",
    "invokedAt": "2026-07-19T10:41:39.418Z"
  },
  {
    "firstName": "Oona",
    "lastName": "Jutila",
    "email": "oona.jutila@example.com",
    "username": "yellowladybug695",
    "password": "jackal",
    "invokedAt": "2026-07-19T11:40:44.388Z"
  }
]