[
  {
    "firstName": "Sean",
    "lastName": "Morel",
    "email": "sean.morel@example.com",
    "username": "orangezebra203",
    "password": "carrie",
    "invokedAt": "2026-03-14T02:03:15.554Z"
  },
  {
    "firstName": "Teodora",
    "lastName": "Tešić",
    "email": "teodora.tesic@example.com",
    "username": "beautifulmouse475",
    "password": "marines",
    "invokedAt": "2026-03-14T04:16:37.312Z"
  },
  {
    "firstName": "Matilda",
    "lastName": "Taylor",
    "email": "matilda.taylor@example.com",
    "username": "angrywolf607",
    "password": "sugar1",
    "invokedAt": "2026-03-14T05:15:48.539Z"
  },
  {
    "firstName": "فاطمه زهرا",
    "lastName": "صدر",
    "email": "ftmhzhr.sdr@example.com",
    "username": "yellowdog469",
    "password": "manny",
    "invokedAt": "2026-03-14T06:00:08.574Z"
  },
  {
    "firstName": "Lonnie",
    "lastName": "Watkins",
    "email": "lonnie.watkins@example.com",
    "username": "yellowmeercat734",
    "password": "jack1",
    "invokedAt": "2026-03-14T06:50:28.793Z"
  },
  {
    "firstName": "Aldaír",
    "lastName": "de Souza",
    "email": "aldair.desouza@example.com",
    "username": "bigtiger228",
    "password": "summer",
    "invokedAt": "2026-03-14T07:24:55.564Z"
  },
  {
    "firstName": "Hans-Wilhelm",
    "lastName": "Fries",
    "email": "hans-wilhelm.fries@example.com",
    "username": "purpleswan782",
    "password": "unknown",
    "invokedAt": "2026-03-14T07:51:41.891Z"
  },
  {
    "firstName": "Stacy",
    "lastName": "Green",
    "email": "stacy.green@example.com",
    "username": "whitepeacock685",
    "password": "pookie",
    "invokedAt": "2026-03-14T08:17:47.730Z"
  },
  {
    "firstName": "De Assis",
    "lastName": "Dias",
    "email": "deassis.dias@example.com",
    "username": "sadswan645",
    "password": "515151",
    "invokedAt": "2026-03-14T08:53:10.099Z"
  },
  {
    "firstName": "Freyja",
    "lastName": "Valseth",
    "email": "freyja.valseth@example.com",
    "username": "tinymeercat788",
    "password": "tennis",
    "invokedAt": "2026-03-14T09:19:03.203Z"
  },
  {
    "firstName": "Nooa",
    "lastName": "Perala",
    "email": "nooa.perala@example.com",
    "username": "tinygoose758",
    "password": "larry",
    "invokedAt": "2026-03-14T09:49:53.769Z"
  },
  {
    "firstName": "Iina",
    "lastName": "Maki",
    "email": "iina.maki@example.com",
    "username": "silvermouse363",
    "password": "awnyce",
    "invokedAt": "2026-03-14T10:01:48.032Z"
  },
  {
    "firstName": "Melvyn",
    "lastName": "Van den Hoorn",
    "email": "melvyn.vandenhoorn@example.com",
    "username": "organicpanda982",
    "password": "leroy",
    "invokedAt": "2026-03-14T10:34:51.550Z"
  },
  {
    "firstName": "Juliane",
    "lastName": "Øvergård",
    "email": "juliane.overgard@example.com",
    "username": "purplepanda763",
    "password": "tommy1",
    "invokedAt": "2026-03-14T10:56:35.047Z"
  },
  {
    "firstName": "Andrew",
    "lastName": "Fleury",
    "email": "andrew.fleury@example.com",
    "username": "sadfish384",
    "password": "express",
    "invokedAt": "2026-03-14T11:17:01.219Z"
  },
  {
    "firstName": "Danko",
    "lastName": "Ognjanović",
    "email": "danko.ognjanovic@example.com",
    "username": "heavybear594",
    "password": "oliver1",
    "invokedAt": "2026-03-14T11:39:33.732Z"
  },
  {
    "firstName": "Özkan",
    "lastName": "Çörekçi",
    "email": "ozkan.corekci@example.com",
    "username": "brownrabbit305",
    "password": "worthy",
    "invokedAt": "2026-03-14T11:53:03.489Z"
  },
  {
    "firstName": "Wayne",
    "lastName": "Ortiz",
    "email": "wayne.ortiz@example.com",
    "username": "organicgoose451",
    "password": "vibrate",
    "invokedAt": "2026-03-14T12:00:35.258Z"
  },
  {
    "firstName": "Gabriella",
    "lastName": "Hunt",
    "email": "gabriella.hunt@example.com",
    "username": "happykoala123",
    "password": "southpar",
    "invokedAt": "2026-03-14T12:58:08.692Z"
  },
  {
    "firstName": "یلدا",
    "lastName": "موسوی",
    "email": "yld.mwswy@example.com",
    "username": "ticklishwolf526",
    "password": "satchmo",
    "invokedAt": "2026-03-14T13:41:51.772Z"
  },
  {
    "firstName": "Abigail",
    "lastName": "Walker",
    "email": "abigail.walker@example.com",
    "username": "angryduck131",
    "password": "trustno1",
    "invokedAt": "2026-03-14T14:04:21.370Z"
  },
  {
    "firstName": "Natalya",
    "lastName": "Davidson",
    "email": "natalya.davidson@example.com",
    "username": "yellowbutterfly956",
    "password": "danzig",
    "invokedAt": "2026-03-14T14:38:59.426Z"
  },
  {
    "firstName": "Selma",
    "lastName": "Hansen",
    "email": "selma.hansen@example.com",
    "username": "redzebra328",
    "password": "iomega",
    "invokedAt": "2026-03-14T14:58:28.161Z"
  },
  {
    "firstName": "Borislav",
    "lastName": "Đokanović",
    "email": "borislav.dokanovic@example.com",
    "username": "smallbird787",
    "password": "indon",
    "invokedAt": "2026-03-14T15:24:21.781Z"
  },
  {
    "firstName": "Eugene",
    "lastName": "Allen",
    "email": "eugene.allen@example.com",
    "username": "sadmouse351",
    "password": "bizzare",
    "invokedAt": "2026-03-14T15:45:48.453Z"
  },
  {
    "firstName": "Félix",
    "lastName": "Guerrero",
    "email": "felix.guerrero@example.com",
    "username": "smalldog793",
    "password": "sakura",
    "invokedAt": "2026-03-14T15:59:19.870Z"
  },
  {
    "firstName": "Stanislava",
    "lastName": "Lapčević",
    "email": "stanislava.lapcevic@example.com",
    "username": "angryladybug753",
    "password": "windsurf",
    "invokedAt": "2026-03-14T16:30:07.156Z"
  },
  {
    "firstName": "Wyatt",
    "lastName": "Kelley",
    "email": "wyatt.kelley@example.com",
    "username": "purpleswan251",
    "password": "lexus",
    "invokedAt": "2026-03-14T16:56:31.486Z"
  },
  {
    "firstName": "Jocieri",
    "lastName": "Silveira",
    "email": "jocieri.silveira@example.com",
    "username": "silverbear422",
    "password": "loaded",
    "invokedAt": "2026-03-14T17:19:01.231Z"
  },
  {
    "firstName": "Likeriya",
    "lastName": "Salko",
    "email": "likeriya.salko@example.com",
    "username": "saddog859",
    "password": "zong",
    "invokedAt": "2026-03-14T17:45:22.954Z"
  },
  {
    "firstName": "Harper",
    "lastName": "Gill",
    "email": "harper.gill@example.com",
    "username": "lazycat429",
    "password": "galary",
    "invokedAt": "2026-03-14T17:58:52.138Z"
  },
  {
    "firstName": "Frosina",
    "lastName": "Monastireckiy",
    "email": "frosina.monastireckiy@example.com",
    "username": "reddog736",
    "password": "rasputin",
    "invokedAt": "2026-03-14T18:36:11.258Z"
  },
  {
    "firstName": "Reinald",
    "lastName": "Lambertz",
    "email": "reinald.lambertz@example.com",
    "username": "bigwolf890",
    "password": "saratoga",
    "invokedAt": "2026-03-14T19:04:29.875Z"
  },
  {
    "firstName": "Verónica",
    "lastName": "Mascareñas",
    "email": "veronica.mascarenas@example.com",
    "username": "blacksnake977",
    "password": "blood",
    "invokedAt": "2026-03-14T19:34:49.653Z"
  },
  {
    "firstName": "Shreya",
    "lastName": "Hiremath",
    "email": "shreya.hiremath@example.com",
    "username": "silverleopard986",
    "password": "kelly1",
    "invokedAt": "2026-03-14T19:50:10.531Z"
  },
  {
    "firstName": "Violeta",
    "lastName": "Ríos",
    "email": "violeta.rios@example.com",
    "username": "smallostrich737",
    "password": "finder",
    "invokedAt": "2026-03-14T19:59:41.166Z"
  }
]